pyatp_buildkit/__init__.py
pyatp_buildkit/build.py
pyatp_buildkit/config.py
pyatp_buildkit/dotdict.py
pyatp_buildkit/error.py
pyatp_buildkit/get-pip.py
pyatp_buildkit/templates/Dockerfile.j2
pyatp_buildkit-1.1.21.dist-info/METADATA
pyatp_buildkit-1.1.21.dist-info/WHEEL
pyatp_buildkit-1.1.21.dist-info/RECORD
