Metadata-Version: 2.1
Name: pyatp-buildkit
Version: 1.1.21
Summary: a iflytek aiab library ...
License: Apache License 2
Author: mjchen
Author-email: mjchen@iflytek.com
Requires-Python: >3.7
Classifier: License :: Other/Proprietary License
Classifier: Programming Language :: Python :: 3
Classifier: Programming Language :: Python :: 3.8
Classifier: Programming Language :: Python :: 3.9
Classifier: Programming Language :: Python :: 3.10
Classifier: Programming Language :: Python :: 3.11
Requires-Dist: jinja2
